hypestat/__init__.py
hypestat/hypestat.py
hypestat-0.0.1.dist-info/licenses/LICENSE
hypestat-0.0.1.dist-info/WHEEL
hypestat-0.0.1.dist-info/METADATA
hypestat-0.0.1.dist-info/RECORD
