Metadata-Version: 2.4
Name: hypestat
Version: 0.0.1
Summary: A Python package to fetch website statistics from Hypestat.com
Author: Luna-Marika Dahl
Author-email: Luna-Marika Dahl <lunamarika@proton.me>
License-Expression: GPL-3.0-or-later
License-File: LICENSE
Classifier: Programming Language :: Python :: 3
Classifier: Operating System :: OS Independent
Requires-Dist: beautifulsoup4>=4.12.0
Requires-Dist: requests>=2.32.5
Requires-Python: >=3.10
Project-URL: HomePage, https://github.com/simplylu/hypestat
Project-URL: Issues, https://github.com/simplylu/hypestat/issues
